source_commercetools/__init__.py
source_commercetools/components.py
source_commercetools/manifest.yaml
source_commercetools/run.py
source_commercetools/schemas/customers.json
source_commercetools/schemas/discount_codes.json
source_commercetools/schemas/orders.json
source_commercetools/schemas/payments.json
source_commercetools/schemas/products.json
source_commercetools/schemas/shared/address.json
source_commercetools/schemas/shared/created_by.json
source_commercetools/schemas/shared/custom.json
source_commercetools/schemas/shared/dimension.json
source_commercetools/schemas/shared/discounted_price_per_quantity.json
source_commercetools/schemas/shared/field_type.json
source_commercetools/schemas/shared/key_reference.json
source_commercetools/schemas/shared/last_modified_by.json
source_commercetools/schemas/shared/localized_string.json
source_commercetools/schemas/shared/money.json
source_commercetools/schemas/shared/price.json
source_commercetools/schemas/shared/price_scoped.json
source_commercetools/schemas/shared/product_data.json
source_commercetools/schemas/shared/product_variant.json
source_commercetools/schemas/shared/reference.json
source_commercetools/schemas/shared/shipping_details.json
source_commercetools/schemas/shared/state.json
source_commercetools/schemas/shared/taxed_item_price.json
source_commercetools/schemas/shared/taxed_price.json
source_commercetools/schemas/shared/taxrate.json
source_commercetools/source.py
airbyte_source_commercetools-0.3.11.dist-info/METADATA
airbyte_source_commercetools-0.3.11.dist-info/WHEEL
airbyte_source_commercetools-0.3.11.dist-info/entry_points.txt
airbyte_source_commercetools-0.3.11.dist-info/RECORD
